XUyG.v
//Gleezell Vina A. Uy S14

`timescale 1ns / 1ps

//Module name: simple circuit
//F = A(CD+B) + BC'

module XUyG(F, A, B, C, D);
    input A, B, C, D;
    output F;
    wire w1, w2, w3, w4, w5;

    and G1(w1, C, D); // w1 = CD
    or G2(w2, w1, B); // w2 = CD + B
    and G3(w3, A, w2); // w3 = A(CD + B)
    not G4(w4, C); // C'
    and G5(w5, B, w4); // BC'
    or G6(F, w3, w5);
endmodule

XUyG_tb.v
//Gleezell Vina A. Uy S14

`timescale 1ns / 1ps

module XUyG_tb();
    wire t_F;
    reg [3:0] t_input;
    integer i;
    //reg t_A, t_B, t_C, t_D;
    
    XUyG dut(t_F, t_input[3], t_input[2], t_input[1], t_input[0]);

    initial 
    begin
        t_input = 4'b0000;
        for (i=1; i<17; i++)
            #10 t_input = i;

    end
        initial
        begin
            $display("Written by Gleezell Vina A. Uy");
            $display("Boolean Function: F = A(CD+B) + BC'");
            $display("Verilog Model: Gate-level modeling");
            $monitor("time = %0d ", $time, "A = %b B = %b C = %b D = %b output_F = %b", t_input[3], t_input[2], t_input[1], t_input[0], t_F);
            $dumpfile("XUyG.vcd");
            $dumpvars();
        end
endmodule

XUyG.vcd
$date
	Tue Jun 20 19:35:04 2023
$end
$version
	Icarus Verilog
$end
$timescale
	1ps
$end
$scope module XUyG_tb $end
$var wire 1 ! t_F $end
$var reg 4 " t_input [3:0] $end
$var integer 32 # i [31:0] $end
$scope module dut $end
$var wire 1 $ A $end
$var wire 1 % B $end
$var wire 1 & C $end
$var wire 1 ' D $end
$var wire 1 ! F $end
$var wire 1 ( w1 $end
$var wire 1 ) w2 $end
$var wire 1 * w3 $end
$var wire 1 + w4 $end
$var wire 1 , w5 $end
$upscope $end
$upscope $end
$enddefinitions $end
$comment Show the parameter values. $end
$dumpall
$end
#0
$dumpvars
0,
1+
0*
0)
0(
0'
0&
0%
0$
b1 #
b0 "
0!
$end
#10000
1'
b10 #
b1 "
#20000
0+
1&
0'
b11 #
b10 "
#30000
1)
1(
1'
b100 #
b11 "
#40000
1!
1,
1+
0(
1%
0&
0'
b101 #
b100 "
#50000
1'
b110 #
b101 "
#60000
0!
0,
0+
1&
0'
b111 #
b110 "
#70000
1(
1'
b1000 #
b111 "
#80000
0)
1+
0(
1$
0%
0&
0'
b1001 #
b1000 "
#90000
1'
b1010 #
b1001 "
#100000
0+
1&
0'
b1011 #
b1010 "
#110000
1!
1*
1)
1(
1'
b1100 #
b1011 "
#120000
1,
1+
0(
1%
0&
0'
b1101 #
b1100 "
#130000
1'
b1110 #
b1101 "
#140000
0,
0+
1&
0'
b1111 #
b1110 "
#150000
1(
1'
b10000 #
b1111 "
#160000
0!
0*
0)
1+
0(
0$
0%
0&
0'
b10001 #
b0 "
